<BackupInst xmlns="http://www.microsoft.com/GroupPolicy/GPOOperations/Manifest"><GPOGuid><![CDATA[{C71638FE-74B1-4884-9C3D-AF9BF3FC6FFC}]]></GPOGuid><GPODomain><![CDATA[formation99.lan]]></GPODomain><GPODomainGuid><![CDATA[{47b2dde1-7d2d-47e6-a90a-fca09d28ecd2}]]></GPODomainGuid><GPODomainController><![CDATA[formation99dc1.formation99.lan]]></GPODomainController><BackupTime><![CDATA[2022-08-08T13:08:56]]></BackupTime><ID><![CDATA[{0D861C4B-37F0-4B51-AF73-22C8B432D3E0}]]></ID><Comment><![CDATA[HAD_Local-Admins_TLeg-Wks]]></Comment><GPODisplayName><![CDATA[HAD_Local-Admins_TLeg-Wks]]></GPODisplayName></BackupInst>
