<BackupInst xmlns="http://www.microsoft.com/GroupPolicy/GPOOperations/Manifest"><GPOGuid><![CDATA[{B36046D8-15F1-40BD-9673-9CFC0D95D979}]]></GPOGuid><GPODomain><![CDATA[DEV.LAB132.LOCAL]]></GPODomain><GPODomainGuid><![CDATA[{21b49d9d-f930-4788-95d4-e09d61dfe9b6}]]></GPODomainGuid><GPODomainController><![CDATA[DEV-WKS-001.DEV.LAB132.LOCAL]]></GPODomainController><BackupTime><![CDATA[2021-10-13T19:20:49]]></BackupTime><ID><![CDATA[{E78DDF6E-8096-4C1B-8C35-ED6DBCEC9DD7}]]></ID><Comment><![CDATA[]]></Comment><GPODisplayName><![CDATA[HAD 2.1 - Security - Auto Update - Up to Win Srv 2012 R2]]></GPODisplayName></BackupInst>
