<BackupInst xmlns="http://www.microsoft.com/GroupPolicy/GPOOperations/Manifest"><GPOGuid><![CDATA[{D7E0978C-345F-463C-9450-8589BF14A5C4}]]></GPOGuid><GPODomain><![CDATA[harden.ad]]></GPODomain><GPODomainGuid><![CDATA[{721b2c21-7be3-45d9-83f1-d375d704aa70}]]></GPODomainGuid><GPODomainController><![CDATA[HAD-DC-01.harden.ad]]></GPODomainController><BackupTime><![CDATA[2023-03-09T16:07:27]]></BackupTime><ID><![CDATA[{89B9E68A-F486-4FA3-B336-7B10B22E714A}]]></ID><Comment><![CDATA[]]></Comment><GPODisplayName><![CDATA[HAD_Auto-Update_S1_Thu_1h_Srv]]></GPODisplayName></BackupInst>
